reflink_copy-0.3.3.dist-info/METADATA
reflink_copy-0.3.3.dist-info/WHEEL
reflink_copy-0.3.3.dist-info/licenses/LICENSE
reflink_copy/__init__.py
reflink_copy/__init__.pyi
reflink_copy/py.typed
reflink_copy/reflink_copy.pypy39-pp73-riscv64-linux-gnu.so
reflink_copy-0.3.3.dist-info/RECORD
