Metadata-Version: 2.4
Name: reflink-copy
Version: 0.3.3
Classifier: Development Status :: 3 - Alpha
Classifier: Programming Language :: Python
Classifier: Programming Language :: Python :: 3
Classifier: Programming Language :: Python :: 3 :: Only
Classifier: Programming Language :: Python :: 3.8
Classifier: Programming Language :: Python :: 3.9
Classifier: Programming Language :: Python :: 3.10
Classifier: Programming Language :: Python :: 3.11
Classifier: Programming Language :: Python :: 3.12
Classifier: Programming Language :: Python :: 3.13
Classifier: Programming Language :: Python :: 3.14
Classifier: Programming Language :: Rust
Classifier: Intended Audience :: Developers
Classifier: License :: OSI Approved :: Apache Software License
Classifier: Operating System :: POSIX :: Linux
Classifier: Operating System :: Microsoft :: Windows
Classifier: Operating System :: MacOS
Classifier: Typing :: Typed
License-File: LICENSE
Summary: Python wrapper for reflink_copy Rust library
Keywords: reflink
Home-Page: https://github.com/iterative/reflink-copy
Author: Saugat Pachhai
License: Apache License 2.0
Requires-Python: >=3.8
Project-URL: Homepage, https://github.com/iterative/reflink-copy
Project-URL: Source, https://github.com/iterative/reflink-copy
